<Properties StartupConfiguration="{80F880F1-D579-7500-70C6-4E62ADBDC437}|">
  <MonoDevelop.Ide.Workbench ActiveDocument="Assets/Scripts/CreateSOData.cs">
    <Files>
      <File FileName="Assets/Scripts/Collections.cs" Line="39" Column="1" />
      <File FileName="Assets/Scripts/AnimController.cs" Line="11" Column="1" />
      <File FileName="Assets/Resources/MouseEvents.cs" Line="13" Column="23" />
      <File FileName="Assets/Scripts/Debugger.cs" Line="9" Column="6" />
      <File FileName="Assets/Scripts/CreateSOData.cs" Line="15" Column="1" />
    </Files>
  </MonoDevelop.Ide.Workbench>
  <MonoDevelop.Ide.DebuggingService.PinnedWatches />
  <MonoDevelop.Ide.Workspace ActiveConfiguration="Debug" />
  <MonoDevelop.Ide.ItemProperties.Assembly-CSharp PreferredExecutionTarget="Unity.Editor" />
  <MonoDevelop.Ide.DebuggingService.Breakpoints>
    <BreakpointStore />
  </MonoDevelop.Ide.DebuggingService.Breakpoints>
  <MultiItemStartupConfigurations />
</Properties>